{"cameraMode":{"drawMode":0,"name":"Shaded","section":"Shading Mode"},"sceneLighting":true,"audioPlay":false,"sceneViewState":{"showFog":true,"showMaterialUpdate":false,"showSkybox":true,"showFlares":true,"showImageEffects":true,"showParticleSystems":true},"in2DMode":false,"pivot":{"x":4.065925598144531,"y":-26.458221435546876,"z":-0.5230370163917542},"rotation":{"x":-0.6287164688110352,"y":-0.3438214361667633,"z":0.36290672421455386,"w":-0.5956518650054932},"size":50.80210494995117,"orthographic":false}